Metadata-Version: 2.1
Name: sanic-pydantic
Version: 1.2.4
Summary: Sanic Pydatic
Home-page: https://nf1s.github.io/sanic-pydantic/
Author: Ahmed Nafies
Author-email: ahmed.nafies@gmail.com
License: MIT
Project-URL: Documentation, https://nf1s.github.io/sanic-pydantic/
Project-URL: Source, https://github.com/nf1s/sanic-pydantic
Platform: UNKNOWN
Classifier: Intended Audience :: Developers
Classifier: Topic :: Utilities
Classifier: License :: OSI Approved :: MIT License
Classifier: Programming Language :: Python :: 3
Classifier: Programming Language :: Python :: 3.6
Classifier: Programming Language :: Python :: 3.7
Classifier: Programming Language :: Python :: 3.8
Requires-Python: >=3.6
Provides-Extra: dev
Provides-Extra: docs
License-File: LICENSE.txt
